deltakit_explorer/__init__.py
deltakit_explorer/_cloud_decoders.py
deltakit_explorer/py.typed
deltakit_explorer/_api/_api_client.py
deltakit_explorer/_api/_api_v2_client.py
deltakit_explorer/_api/_auth.py
deltakit_explorer/_api/_client.py
deltakit_explorer/_api/_gql_client.py
deltakit_explorer/_gates/_gate_sets.py
deltakit_explorer/_utils/_decorators.py
deltakit_explorer/_utils/_logging.py
deltakit_explorer/_utils/_utils.py
deltakit_explorer/analysis/__init__.py
deltakit_explorer/analysis/_analysis.py
deltakit_explorer/analysis/_lambda.py
deltakit_explorer/analysis/_leppr.py
deltakit_explorer/analysis/_quops.py
deltakit_explorer/codes/__init__.py
deltakit_explorer/codes/_bivariate_bicycle_code.py
deltakit_explorer/codes/_logicals.py
deltakit_explorer/codes/_repetition_code.py
deltakit_explorer/codes/_stabiliser.py
deltakit_explorer/codes/_css/_css_code.py
deltakit_explorer/codes/_css/_css_code_experiment_circuit.py
deltakit_explorer/codes/_css/_css_stage.py
deltakit_explorer/codes/_css/_detectors.py
deltakit_explorer/codes/_css/_experiment_circuit.py
deltakit_explorer/codes/_css/_observables.py
deltakit_explorer/codes/_css/_stabiliser_code.py
deltakit_explorer/codes/_css/_stabiliser_helper_functions.py
deltakit_explorer/codes/_planar_code/__init__.py
deltakit_explorer/codes/_planar_code/_planar_code.py
deltakit_explorer/codes/_planar_code/_rotated_planar_code.py
deltakit_explorer/codes/_planar_code/_unrotated_planar_code.py
deltakit_explorer/codes/_planar_code/_unrotated_toric_code.py
deltakit_explorer/codes/_schedules/__init__.py
deltakit_explorer/codes/_schedules/_rotated_planar_code_schedules.py
deltakit_explorer/codes/_schedules/_schedule_order.py
deltakit_explorer/codes/_schedules/_unrotated_planar_code_schedules.py
deltakit_explorer/data/__init__.py
deltakit_explorer/data/_converter.py
deltakit_explorer/data/_data_analysis.py
deltakit_explorer/enums/__init__.py
deltakit_explorer/enums/_api_enums.py
deltakit_explorer/enums/_basic_enums.py
deltakit_explorer-0.6.2.dist-info/licenses/LICENSE
deltakit_explorer-0.6.2.dist-info/METADATA
deltakit_explorer-0.6.2.dist-info/WHEEL
deltakit_explorer-0.6.2.dist-info/top_level.txt
deltakit_explorer-0.6.2.dist-info/RECORD
